{ 
    "EncounterTable" :
    { 
        "Area1" :
        {
            "playerSquare1" : {
                "Dice1" : "Dice1",
                "Dice2" : "Dice2",
                "Dice3" : "Dice3",
                "Dice4" : "Dice4",
                "Dice5" : "Dice5",
                "Dice6" : "Dice6"

                             },
            "playerSquare2" : {
                "Dice1" : "Dice1",
                "Dice2" : "Dice2",
                "Dice3" : "Dice3",
                "Dice4" : "Dice3",
                "Dice5" : "Dice5",
                "Dice6" : "Dice6"
            }
            

        },
        "Area 2" :
        {

        },
    
        "Area 3" :
        {

        },
        "Area 4" :
        {

        },
        "Area 5" : 
        {

        }
    }
}

